TrustDecoders.py
trustdecoders-1.9.5.dist-info/LICENSE
trustdecoders-1.9.5.dist-info/METADATA
trustdecoders-1.9.5.dist-info/WHEEL
trustdecoders-1.9.5.dist-info/RECORD
